{"target":"http://pubannotation.org/docs/sourcedb/PMC/sourceid/2065877/divs/27","sourcedb":"PMC","sourceid":"2065877","divid":27,"text":"Summary of Analysis Performed on Wild-Type and LMP1 Transgenic Lymphomas","project":"pmc-enju-pas","denotations":[{"id":"enju_T0","span":{"begin":0,"end":7},"obj":"NN"},{"id":"enju_T1","span":{"begin":8,"end":10},"obj":"IN"},{"id":"enju_T2","span":{"begin":11,"end":19},"obj":"NN"},{"id":"enju_T3","span":{"begin":20,"end":29},"obj":"NNP"},{"id":"enju_T4","span":{"begin":30,"end":32},"obj":"IN"},{"id":"enju_T5","span":{"begin":33,"end":42},"obj":"NNP"},{"id":"enju_T6","span":{"begin":43,"end":46},"obj":"CC"},{"id":"enju_T7","span":{"begin":47,"end":51},"obj":"NN"},{"id":"enju_T8","span":{"begin":52,"end":62},"obj":"JJ"},{"id":"enju_T9","span":{"begin":63,"end":72},"obj":"NN"}],"relations":[{"id":"enju_R0","pred":"arg1Of","subj":"enju_T0","obj":"enju_T1"},{"id":"enju_R1","pred":"arg2Of","subj":"enju_T3","obj":"enju_T1"},{"id":"enju_R2","pred":"arg1Of","subj":"enju_T3","obj":"enju_T2"},{"id":"enju_R3","pred":"arg1Of","subj":"enju_T0","obj":"enju_T4"},{"id":"enju_R4","pred":"arg2Of","subj":"enju_T6","obj":"enju_T4"},{"id":"enju_R5","pred":"arg1Of","subj":"enju_T5","obj":"enju_T6"},{"id":"enju_R6","pred":"arg2Of","subj":"enju_T9","obj":"enju_T6"},{"id":"enju_R7","pred":"arg1Of","subj":"enju_T9","obj":"enju_T7"},{"id":"enju_R8","pred":"arg1Of","subj":"enju_T9","obj":"enju_T8"}]}